rwkv/__init__.py
rwkv/model.py
rwkv/rwkv_tokenizer.py
rwkv/rwkv_vocab_v20230424.txt
rwkv/utils.py
rwkv/cuda/gemm_fp16_cublas.cpp
rwkv/cuda/operators.cu
rwkv/cuda/rwkv5.cu
rwkv/cuda/rwkv5_op.cpp
rwkv/cuda/rwkv6.cu
rwkv/cuda/rwkv6_op.cpp
rwkv/cuda/rwkv7.cu
rwkv/cuda/rwkv7_op.cpp
rwkv/cuda/wrapper.cpp
rwkv-0.8.31.dist-info/licenses/LICENSE
rwkv-0.8.31.dist-info/METADATA
rwkv-0.8.31.dist-info/WHEEL
rwkv-0.8.31.dist-info/top_level.txt
rwkv-0.8.31.dist-info/RECORD
